Day 6/binary_to_bcd/binary_to_bcd.v
module binary_to_bcd(input[3:0]b, output[3:0]tens, output[3:0]ones);
        assign tens = (b>9) ? 4'b0001 : 4'b0000; 
        assign ones = (b > 9) ? (b - 4'd10) : b;
endmodule

Day 6/binary_to_bcd/binary_to_bcd_tb.v
module binary_to_bcd_tb;
         reg[3:0]b;
         wire[3:0]tens;
         wire[3:0]ones;
    binary_to_bcd uut(.b(b), .tens(tens), .ones(ones));
  initial begin
    $monitor("Time=%0t,  b=%b | tens=%b ones=%b ", $time, b,tens,ones);
    $dumpfile("binary_to_bcd.vcd");
    $dumpvars(0, binary_to_bcd_tb);
     b = 4'd0;  #10;
     b = 4'd1;  #10;
     b = 4'd5;  #10;
     b = 4'd8;  #10;
     b = 4'd11; #10;
     b = 4'd12; #10;
     b = 4'd13; #10;
     b = 4'd14; #10;
     $finish;
    end
endmodule

Day 6/binary_to_bcd/binary_to_bcd.vcd
$date
	Fri Oct 24 10:59:26 2025
$end
$version
	Icarus Verilog
$end
$timescale
	1s
$end
$scope module binary_to_bcd_tb $end
$var wire 4 ! tens [3:0] $end
$var wire 4 " ones [3:0] $end
$var reg 4 # b [3:0] $end
$scope module uut $end
$var wire 4 $ b [3:0] $end
$var wire 4 % tens [3:0] $end
$var wire 4 & ones [3:0] $end
$upscope $end
$upscope $end
$enddefinitions $end
$comment Show the parameter values. $end
$dumpall
$end
#0
$dumpvars
b0 &
b0 %
b0 $
b0 #
b0 "
b0 !
$end
#10
b1 "
b1 &
b1 #
b1 $
#20
b101 "
b101 &
b101 #
b101 $
#30
b1000 "
b1000 &
b1000 #
b1000 $
#40
b1 !
b1 %
b1 "
b1 &
b1011 #
b1011 $
#50
b10 "
b10 &
b1100 #
b1100 $
#60
b11 "
b11 &
b1101 #
b1101 $
#70
b100 "
b100 &
b1110 #
b1110 $
