Day 8/Registers/PIPO_register/PIPO_register.v
module PIPO_register(
        input [3:0]d,
        input clk,
        input rst,
        output y0,
        output y1,
        output y2,
        output y3 );

    reg [3:0]sr = 4'b0000;

  always@(posedge clk)
     begin
      if(rst)
          sr <= 4'b0000;
      else
          sr <= d;
     end
  
   assign y0 = sr[0];
   assign y1 = sr[1];
   assign y2 = sr[2];
   assign y3 = sr[3];
endmodule

Day 8/Registers/PIPO_register/PIPO_register_tb.v
module PIPO_register_tb;

     reg [3:0]d;
     reg rst;
     reg clk;
     wire y0;
     wire y1;
     wire y2;
     wire y3;

 PIPO_register uut(.d(d), .rst(rst), .clk(clk), .y0(y0), .y1(y1), .y2(y2), .y3(y3) );

  initial clk = 0;
  always #5 clk = ~clk;


initial begin

   $monitor("Time = %0t, rst = %b, clk = %b, d = %b, y0 = %b, y1 = %b, y2 = %b, y3 = %b", $time,rst,clk,d,y0,y1,y2,y3);

   $dumpfile("PIPO_register.vcd");
   $dumpvars(0, PIPO_register_tb);

   rst = 1; d = 4'b0000;
    #10 rst = 0;

    #10 d = 4'b1111;
    #10 d = 4'b1011;
    #10 d = 4'b1001;
    #10 d = 4'b0101;

    #20;
    $finish;
end
endmodule

Day 8/Registers/PIPO_register/PIPO_register.vcd
$date
	Thu Feb 12 18:42:04 2026
$end
$version
	Icarus Verilog
$end
$timescale
	1s
$end
$scope module PIPO_register_tb $end
$var wire 1 ! y3 $end
$var wire 1 " y2 $end
$var wire 1 # y1 $end
$var wire 1 $ y0 $end
$var reg 1 % clk $end
$var reg 4 & d [3:0] $end
$var reg 1 ' rst $end
$scope module uut $end
$var wire 1 % clk $end
$var wire 4 ( d [3:0] $end
$var wire 1 ' rst $end
$var wire 1 ! y3 $end
$var wire 1 " y2 $end
$var wire 1 # y1 $end
$var wire 1 $ y0 $end
$var reg 4 ) sr [3:0] $end
$upscope $end
$upscope $end
$enddefinitions $end
$comment Show the parameter values. $end
$dumpall
$end
#0
$dumpvars
b0 )
b0 (
1'
b0 &
0%
0$
0#
0"
0!
$end
#5
1%
#10
0%
0'
#15
1%
#20
0%
b1111 &
b1111 (
#25
1$
1#
1"
1!
b1111 )
1%
#30
0%
b1011 &
b1011 (
#35
0"
b1011 )
1%
#40
0%
b1001 &
b1001 (
#45
0#
b1001 )
1%
#50
0%
b101 &
b101 (
#55
1"
0!
b101 )
1%
