Day 6/binary_to_excess3/binary_to_excess3.v
module b_to_e( input[3:0]b , output[3:0]e );
    assign e = b + 4'b0011;
endmodule

Day 6/binary_to_excess3/binary_to_excess3_tb.v
module b_to_e_tb;
   reg[3:0]b;
   wire[3:0]e;
  b_to_e uut(.b(b), .e(e) );
 initial begin 
	  $monitor("Time=%0t, b=%b | e=%b ", $time, b,e);
	  $dumpfile("b_to_e.vcd");
	  $dumpvars(0, b_to_e_tb);
	b = 4'b0000; #10
	b = 4'b0001; #10
	b = 4'b0010; #10
        b = 4'b0011; #10
        b = 4'b0100; #10
        b = 4'b0101; #10
        b = 4'b0110; #10
        b = 4'b0111; #10

       $finish;
     end
endmodule

Day 6/binary_to_excess3/b_to_e.vcd
$date
	Fri Oct 24 04:38:21 2025
$end
$version
	Icarus Verilog
$end
$timescale
	1s
$end
$scope module b_to_e_tb $end
$var wire 4 ! e [3:0] $end
$var reg 4 " b [3:0] $end
$scope module uut $end
$var wire 4 # b [3:0] $end
$var wire 4 $ e [3:0] $end
$upscope $end
$upscope $end
$enddefinitions $end
$comment Show the parameter values. $end
$dumpall
$end
#0
$dumpvars
b11 $
b0 #
b0 "
b11 !
$end
#10
b100 !
b100 $
b1 "
b1 #
#20
b101 !
b101 $
b10 "
b10 #
#30
b110 !
b110 $
b11 "
b11 #
#40
b111 !
b111 $
b100 "
b100 #
#50
b1000 !
b1000 $
b101 "
b101 #
#60
b1001 !
b1001 $
b110 "
b110 #
#70
b1010 !
b1010 $
b111 "
b111 #
