Day 6/gray_to_binary/g_to_b.v
module g_to_b(input[2:0]g , output[2:0]b);
    assign b[2] = g[2];
    assign b[1] = b[2]^g[1];
    assign b[0] = b[1]^g[0];
endmodule

Day 6/gray_to_binary/g_to_b_tb.v
module g_to_b_tb;
   reg [2:0]g;
   wire [2:0]b;
   g_to_b uut (.g(g), .b(b));
 initial begin
    $monitor("Time=%0t, g=%b | b=%b ", $time, g,b );
    $dumpfile("g_to_b.vcd");
    $dumpvars(0, g_to_b_tb);
      g = 3'b000; #10;
      g = 3'b001; #10;
      g = 3'b010; #10;
      g = 3'b011; #10;
      g = 3'b100; #10;
      g = 3'b101; #10;
      g = 3'b110; #10;
      g = 3'b111; #10;
      $finish;
    end
endmodule

Day 6/gray_to_binary/g_to_b.vcd
$date
	Thu Oct 23 18:37:08 2025
$end
$version
	Icarus Verilog
$end
$timescale
	1s
$end
$scope module g_to_b_tb $end
$var wire 3 ! b [2:0] $end
$var reg 3 " g [2:0] $end
$scope module uut $end
$var wire 3 # g [2:0] $end
$var wire 3 $ b [2:0] $end
$upscope $end
$upscope $end
$enddefinitions $end
$comment Show the parameter values. $end
$dumpall
$end
#0
$dumpvars
b0 $
b0 #
b0 "
b0 !
$end
#10
b1 !
b1 $
b1 "
b1 #
#20
b11 !
b11 $
b10 "
b10 #
#30
b10 !
b10 $
b11 "
b11 #
#40
b111 !
b111 $
b100 "
b100 #
#50
b110 !
b110 $
b101 "
b101 #
#60
b100 !
b100 $
b110 "
b110 #
#70
b101 !
b101 $
b111 "
b111 #
