DAY 2/full_adder/full_adder.v
module full_adder(input A,B,Cin , output Sum , Carry );
     assign w1 = A ^ B;
     assign w2 = A & B;
     assign w3 = w1 & Cin;
     assign Sum = w1 ^ Cin;
     assign Carry = w2 | w3;
endmodule

DAY 2/full_adder/full_adder_tb.v
module full_adder_tb();
    reg A,B,Cin;
    wire Sum,Carry;
  full_adder uut(.A(A),.B(B),.Cin(Cin),.Sum(Sum),.Carry(Carry));
 initial begin
    A = 0 ; B =0 ;Cin = 0; #10
    A = 0 ; B =0 ;Cin = 1; #10
    A = 0 ; B =1 ;Cin = 0; #10
    A = 0 ; B =1 ;Cin = 1; #10
    A = 1 ; B =0 ;Cin = 0; #10
    A = 1 ; B =0 ;Cin = 1; #10
    A = 1 ; B =1 ;Cin = 0; #10
    A = 1 ; B =1 ;Cin = 1; #10
  $finish;
 end
 initial begin
    $monitor("Time=%0t , A =%b, B=%b, Cin=%b , Sum=%b , Carry=%b", $time , A,B,Cin,Sum,Carry);
    $dumpfile("full_adder.vcd");
    $dumpvars(0 , full_adder_tb);
 end   
endmodule

DAY 2/full_adder/full_adder.vcd
$date
	Sun Oct 12 18:35:12 2025
$end
$version
	Icarus Verilog
$end
$timescale
	1s
$end
$scope module full_adder_tb $end
$var wire 1 ! Sum $end
$var wire 1 " Carry $end
$var reg 1 # A $end
$var reg 1 $ B $end
$var reg 1 % Cin $end
$scope module uut $end
$var wire 1 # A $end
$var wire 1 $ B $end
$var wire 1 " Carry $end
$var wire 1 % Cin $end
$var wire 1 ! Sum $end
$var wire 1 & w1 $end
$var wire 1 ' w2 $end
$var wire 1 ( w3 $end
$upscope $end
$upscope $end
$enddefinitions $end
$comment Show the parameter values. $end
$dumpall
$end
#0
$dumpvars
0(
0'
0&
0%
0$
0#
0"
0!
$end
#10
1!
1%
#20
1&
0%
1$
#30
1"
1(
0!
1%
#40
0"
0(
1!
0%
0$
1#
#50
1"
1(
0!
1%
#60
0(
0&
1'
0%
1$
#70
1!
1%
