Day 8/Registers/SIPO_register/SIPO_register.v
module SIPO_register(
    input d,
    input clk,
    input rst,
    output y1,
    output y2,
    output y3,
    output y4
);

    reg [3:0]sr = 4'b0000;

    always @(posedge clk) begin
        if(rst)
            sr <= 4'b0000;
        else
            sr <= { sr[2:0], d };
    end

    assign y1 = sr[3];
    assign y2 = sr[2];
    assign y3 = sr[1];
    assign y4 = sr[0];

endmodule

Day 8/Registers/SIPO_register/SIPO_register_tb.v
module SIPO_register_tb;
        reg d;
	reg clk;
	reg rst;
        wire y1,y2,y3,y4;


	SIPO_register uut(.clk(clk), .rst(rst), .d(d), .y1(y1), .y2(y2), .y3(y3), .y4(y4) );

	 always #5 clk = ~clk;

initial begin

     $monitor("Time =%0t, rst=%b | clk =%b | d=%b | y1=%b | y2=%b | y3=%b | y4=%b ", $time,rst,clk,d,y1,y2,y3,y4);
     $dumpfile("SIPO_regiser.vcd");
     $dumpvars( 0, SIPO_register_tb );

     clk = 0; rst = 1; d = 0;
      #10 rst = 0;

     #10 d = 1;
     #10 d = 0;
     #10 d = 1;
     #10 d = 0;

     #20;

    $finish;
  end
endmodule

Day 8/Registers/SIPO_register/SIPO_regiser.vcd
$date
	Thu Feb 12 18:56:38 2026
$end
$version
	Icarus Verilog
$end
$timescale
	1s
$end
$scope module SIPO_register_tb $end
$var wire 1 ! y4 $end
$var wire 1 " y3 $end
$var wire 1 # y2 $end
$var wire 1 $ y1 $end
$var reg 1 % clk $end
$var reg 1 & d $end
$var reg 1 ' rst $end
$scope module uut $end
$var wire 1 % clk $end
$var wire 1 & d $end
$var wire 1 ' rst $end
$var wire 1 ! y4 $end
$var wire 1 " y3 $end
$var wire 1 # y2 $end
$var wire 1 $ y1 $end
$var reg 4 ( sr [3:0] $end
$upscope $end
$upscope $end
$enddefinitions $end
$comment Show the parameter values. $end
$dumpall
$end
#0
$dumpvars
b0 (
1'
0&
0%
0$
0#
0"
0!
$end
#5
1%
#10
0%
0'
#15
1%
#20
0%
1&
#25
1!
b1 (
1%
#30
0%
0&
#35
1"
0!
b10 (
1%
#40
0%
1&
#45
1#
0"
1!
b101 (
1%
#50
0%
0&
#55
1$
0#
1"
0!
b1010 (
1%
#60
0%
#65
0$
1#
0"
b100 (
1%
