Day 7/D_flip_flop/D_ff.v
module d_ff(input D, input clk, input reset, output reg Q);
    always@(posedge clk or posedge reset)
     begin
       if(reset)
          Q <= 0;
       else 
          Q <= D;
     end
endmodule

Day 7/D_flip_flop/D_ff_tb.v
module d_ff_tb;
    reg D;
    reg clk;
    reg reset;
    wire Q;
  d_ff uut(.D(D), .clk(clk), .reset(reset), .Q(Q) );
   
   always #5 clk = ~clk;
  initial begin
    $monitor("Time=%0t, clk=%b | D=%b | Q=%b |", $time, clk,D,Q );
    $dumpfile("d_ff.vcd");
    $dumpvars(0, d_ff_tb);
   
   clk = 0; reset = 1; D = 0;
    #10 reset = 0; 
    #10 D = 1;
    #10 D = 0;
    #10 D = 1;
    #10 $finish; 
  end
endmodule

Day 7/D_flip_flop/d_ff.vcd
$date
	Mon Oct 27 05:40:21 2025
$end
$version
	Icarus Verilog
$end
$timescale
	1s
$end
$scope module d_ff_tb $end
$var wire 1 ! Q $end
$var reg 1 " D $end
$var reg 1 # clk $end
$var reg 1 $ reset $end
$scope module uut $end
$var wire 1 " D $end
$var wire 1 # clk $end
$var wire 1 $ reset $end
$var reg 1 ! Q $end
$upscope $end
$upscope $end
$enddefinitions $end
$comment Show the parameter values. $end
$dumpall
$end
#0
$dumpvars
1$
0#
0"
0!
$end
#5
1#
#10
0#
0$
#15
1#
#20
0#
1"
#25
1!
1#
#30
0#
0"
#35
0!
1#
#40
0#
1"
#45
1!
1#
