DAY3/2to1_Mux/21_Mux.v
module mux(input a,b,s , output y);
   assign w1 = (~s) & a;
   assign w2 = s & b;
   assign y = w1 | w2;
endmodule

DAY3/2to1_Mux/21_Mux_tb.v
module mux_tb();
   reg a,b,s;
   wire y;
   mux uut(.a(a),.b(b),.s(s),.y(y));
 initial begin
    s = 0 ; a=0 ; b=0; #10
    s = 0 ; a=0 ; b=1; #10
    s = 0 ; a=1 ; b=0; #10 
    s = 0 ; a=1 ; b=1; #10
    s = 1 ; a=0 ; b=0; #10
    s = 1 ; a=0 ; b=1; #10
    s = 1 ; a=1 ; b=0; #10
    s = 1 ; a=1 ; b=1; #10
  $finish;
 end
   initial begin  
    $monitor("Time =%0t, s=%b,a=%b,b=%b,y=%b", $time,s,a,b,y);
    $dumpfile("mux.vcd");
    $dumpvars(0, mux_tb);
   end
endmodule

DAY3/2to1_Mux/mux.vcd
$date
	Mon Oct 13 09:08:23 2025
$end
$version
	Icarus Verilog
$end
$timescale
	1s
$end
$scope module mux_tb $end
$var wire 1 ! y $end
$var reg 1 " a $end
$var reg 1 # b $end
$var reg 1 $ s $end
$scope module uut $end
$var wire 1 " a $end
$var wire 1 # b $end
$var wire 1 $ s $end
$var wire 1 % w1 $end
$var wire 1 & w2 $end
$var wire 1 ! y $end
$upscope $end
$upscope $end
$enddefinitions $end
$comment Show the parameter values. $end
$dumpall
$end
#0
$dumpvars
0&
0%
0$
0#
0"
0!
$end
#10
1#
#20
1!
1%
0#
1"
#30
1#
#40
0!
0%
0#
0"
1$
#50
1!
1&
1#
#60
0!
0&
0#
1"
#70
1!
1&
1#
