Day 6/bcd_to_7segment/bcd_to_7segment.v
module bcd_to_seven_seg(input[3:0]bcd, output reg[6:0]seven_seg);
    always @(*) begin
        case(bcd)
            4'b0000: seven_seg = 7'b1111110; 
            4'b0001: seven_seg = 7'b0110000; 
            4'b0010: seven_seg = 7'b1101101; 
            4'b0011: seven_seg = 7'b1111001; 
            4'b0100: seven_seg = 7'b0110011; 
            4'b0101: seven_seg = 7'b1011011; 
            4'b0110: seven_seg = 7'b1011111; 
            4'b0111: seven_seg = 7'b1110000;
            4'b1000: seven_seg = 7'b1111111; 
            4'b1001: seven_seg = 7'b1111011; 
            default: seven_seg = 7'b0000000; 
        endcase
    end
endmodule

Day 6/bcd_to_7segment/bcd_to_7segment_tb.v
module bcd_to_seven_seg_tb;
    reg [3:0]bcd;
    wire [6:0]seven_seg;
   bcd_to_seven_seg uut (.bcd(bcd), .seven_seg(seven_seg));
  initial begin
	$monitor("Time=%0t, bcd=%b | seven_seg=%b", $time, bcd, seven_seg);    
        $dumpfile("bcd_to_seven_seg.vcd");
        $dumpvars(0, bcd_to_seven_seg_tb);

        bcd = 4'b0000;
        repeat (10) begin
            #10  bcd = bcd + 1;  
        end 

        $finish;           
  end
endmodule

Day 6/bcd_to_7segment/bcd_to_seven_seg.vcd
$date
	Sat Oct 25 06:16:45 2025
$end
$version
	Icarus Verilog
$end
$timescale
	1s
$end
$scope module bcd_to_seven_seg_tb $end
$var wire 7 ! seven_seg [6:0] $end
$var reg 4 " bcd [3:0] $end
$scope module uut $end
$var wire 4 # bcd [3:0] $end
$var reg 7 $ seven_seg [6:0] $end
$upscope $end
$upscope $end
$enddefinitions $end
$comment Show the parameter values. $end
$dumpall
$end
#0
$dumpvars
b1111110 $
b0 #
b0 "
b1111110 !
$end
#10
b110000 !
b110000 $
b1 "
b1 #
#20
b1101101 !
b1101101 $
b10 "
b10 #
#30
b1111001 !
b1111001 $
b11 "
b11 #
#40
b110011 !
b110011 $
b100 "
b100 #
#50
b1011011 !
b1011011 $
b101 "
b101 #
#60
b1011111 !
b1011111 $
b110 "
b110 #
#70
b1110000 !
b1110000 $
b111 "
b111 #
#80
b1111111 !
b1111111 $
b1000 "
b1000 #
#90
b1111011 !
b1111011 $
b1001 "
b1001 #
#100
b0 !
b0 $
b1010 "
b1010 #
