DAY 2/full_subtractor/full_subtractor.v
module full_subtractor(input A,B,Bin , output Diff , Borrow);
    assign w1 = A^B;
    assign Diff = w1^Bin;
    assign w2 = (~w1) & Bin;
    assign w3 = B & (~A);
    assign Borrow = w2 | w3;
endmodule

DAY 2/full_subtractor/full_subtractor_tb.v
module full_subtractor_tb();
    reg A,B,Bin;
    wire Diff , Borrow;
  full_subtractor uut(.A(A),.B(B),.Bin(Bin),.Diff(Diff),.Borrow(Borrow));
 initial begin
   A=0 ; B=0 ; Bin=0; #10
   A=0 ; B=0 ; Bin=1; #10
   A=0 ; B=1 ; Bin=0; #10
   A=0 ; B=1 ; Bin=1; #10
   A=1 ; B=0 ; Bin=0; #10
   A=1 ; B=0 ; Bin=1; #10
   A=1 ; B=1 ; Bin=0; #10
   A=1 ; B=1 ; Bin=1; #10
  $finish;
 end
  initial begin
    $monitor("Time=%0t , A=%b, B=%b, Bin=%b, Diff=%b, Borrow=%b", $time , A,B,Bin,Diff,Borrow); 
    $dumpfile("full_subtractor.vcd");
    $dumpvars(0,full_subtractor_tb);
  end
endmodule

DAY 2/full_subtractor/full_subtractor.vcd
$date
	Sun Oct 12 19:40:08 2025
$end
$version
	Icarus Verilog
$end
$timescale
	1s
$end
$scope module full_subtractor_tb $end
$var wire 1 ! Diff $end
$var wire 1 " Borrow $end
$var reg 1 # A $end
$var reg 1 $ B $end
$var reg 1 % Bin $end
$scope module uut $end
$var wire 1 # A $end
$var wire 1 $ B $end
$var wire 1 % Bin $end
$var wire 1 " Borrow $end
$var wire 1 ! Diff $end
$var wire 1 & w1 $end
$var wire 1 ' w2 $end
$var wire 1 ( w3 $end
$upscope $end
$upscope $end
$enddefinitions $end
$comment Show the parameter values. $end
$dumpall
$end
#0
$dumpvars
0(
0'
0&
0%
0$
0#
0"
0!
$end
#10
1"
1!
1'
1%
#20
0'
1&
1(
0%
1$
#30
0!
1%
#40
0"
1!
0(
0%
0$
1#
#50
0!
1%
#60
0&
0%
1$
#70
1"
1!
1'
1%
