Day 6/binary_to_gray/binary_to_gray.v
module binary_to_gray( input[2:0] b, output[2:0] g );
      assign g[2] = b[2];
      assign g[1] = b[2]^b[1];
      assign g[0] = b[1]^b[0];
endmodule

Day 6/binary_to_gray/b_to_g_tb.v
module b_to_g_tb;
   reg [2:0]b;
   wire [2:0]g;
  binary_to_gray uut (.b(b), .g(g));
 initial begin
    $monitor("Time=%0t, b=%b | g=%b ", $time, b,g );
    $dumpfile("b_to_g.vcd");
    $dumpvars(0, b_to_g_tb);
      b = 3'b000; #10;
      b = 3'b001; #10;
      b = 3'b010; #10;
      b = 3'b011; #10;
      b = 3'b100; #10;
      b = 3'b101; #10;
      b = 3'b110; #10;
      b = 3'b111; #10;

      $finish;
    end
endmodule

cd Day 6/binary_to_gray/b_to_g.vcd
$date
	Thu Oct 23 18:07:54 2025
$end
$version
	Icarus Verilog
$end
$timescale
	1s
$end
$scope module b_to_g_tb $end
$var wire 3 ! g [2:0] $end
$var reg 3 " b [2:0] $end
$scope module uut $end
$var wire 3 # b [2:0] $end
$var wire 3 $ g [2:0] $end
$upscope $end
$upscope $end
$enddefinitions $end
$comment Show the parameter values. $end
$dumpall
$end
#0
$dumpvars
b0 $
b0 #
b0 "
b0 !
$end
#10
b1 !
b1 $
b1 "
b1 #
#20
b11 !
b11 $
b10 "
b10 #
#30
b10 !
b10 $
b11 "
b11 #
#40
b110 !
b110 $
b100 "
b100 #
#50
b111 !
b111 $
b101 "
b101 #
#60
b101 !
b101 $
b110 "
b110 #
#70
b100 !
b100 $
b111 "
b111 #
